{"id":"5afd62c82e7bcbe720ce0919","name":"Pembersihan Damija","desc":"","descData":null,"closed":false,"idOrganization":null,"invited":false,"limits":{"attachments":{"perBoard":{"status":"ok","disableAt":34200,"warnAt":32400}},"boards":{"totalMembersPerBoard":{"status":"ok","disableAt":1520,"warnAt":1440}},"cards":{"openPerBoard":{"status":"ok","disableAt":4750,"warnAt":4500},"totalPerBoard":{"status":"ok","disableAt":1900000,"warnAt":1800000}},"checklists":{"perBoard":{"status":"ok","disableAt":1900000,"warnAt":1800000}},"customFields":{"perBoard":{"status":"ok","disableAt":48,"warnAt":45}},"labels":{"perBoard":{"status":"ok","disableAt":950,"warnAt":900}},"lists":{"openPerBoard":{"status":"ok","disableAt":475,"warnAt":450},"totalPerBoard":{"status":"ok","disableAt":2850,"warnAt":2700}}},"pinned":false,"starred":false,"url":"https://trello.com/b/XPhODWYc/pembersihan-damija","prefs":{"permissionLevel":"private","voting":"disabled","comments":"members","invitations":"members","selfJoin":false,"cardCovers":true,"cardAging":"regular","calendarFeedEnabled":false,"background":"blue","backgroundImage":null,"backgroundImageScaled":null,"backgroundTile":false,"backgroundBrightness":"dark","backgroundColor":"#0079BF","backgroundBottomColor":"#0079BF","backgroundTopColor":"#0079BF","canBePublic":true,"canBeOrg":true,"canBePrivate":true,"canInvite":true},"invitations":[],"shortLink":"XPhODWYc","subscribed":false,"labelNames":{"green":"","yellow":"","orange":"","red":"","purple":"","blue":"","sky":"","lime":"","pink":"","black":""},"powerUps":[],"dateLastActivity":"2018-06-18T13:45:46.037Z","dateLastView":"2018-06-18T13:45:56.406Z","shortUrl":"https://trello.com/b/XPhODWYc","idTags":[],"datePluginDisable":null,"actions":[{"id":"5b27b78a7218d1144d650764","idMemberCreator":"5aeeceaad0de5dcfb6dede5b","data":{"listAfter":{"name":"Masalah","id":"5afd62d1729e8a07ec91e3db"},"listBefore":{"name":"Pekerjaan","id":"5afd62d038a3f9714e1973ec"},"board":{"shortLink":"XPhODWYc","name":"Pembersihan Damija","id":"5afd62c82e7bcbe720ce0919"},"card":{"shortLink":"0jxjJ2dH","idShort":4,"name":"Galian Selokan","id":"5b27b745a92449ac2c2b81cc","idList":"5afd62d1729e8a07ec91e3db"},"old":{"idList":"5afd62d038a3f9714e1973ec"}},"type":"updateCard","date":"2018-06-18T13:45:46.039Z","limits":{},"memberCreator":{"id":"5aeeceaad0de5dcfb6dede5b","avatarHash":null,"avatarUrl":null,"fullName":"edi","initials":"E","username":"edi287"}},{"id":"5b27b7871e89c30d52ea4cd9","idMemberCreator":"5aeeceaad0de5dcfb6dede5b","data":{"listAfter":{"name":"Selesai","id":"5afd6465b03c84f27b5ae1e0"},"listBefore":{"name":"Pekerjaan","id":"5afd62d038a3f9714e1973ec"},"board":{"shortLink":"XPhODWYc","name":"Pembersihan Damija","id":"5afd62c82e7bcbe720ce0919"},"card":{"shortLink":"zKOFz6O1","idShort":1,"name":"Pemotongan rumput","id":"5afd62ffde88f325936678d5","idList":"5afd6465b03c84f27b5ae1e0"},"old":{"idList":"5afd62d038a3f9714e1973ec"}},"type":"updateCard","date":"2018-06-18T13:45:43.082Z","limits":{},"memberCreator":{"id":"5aeeceaad0de5dcfb6dede5b","avatarHash":null,"avatarUrl":null,"fullName":"edi","initials":"E","username":"edi287"}},{"id":"5b27b77d9762dc50dee9673d","idMemberCreator":"5aeeceaad0de5dcfb6dede5b","data":{"member":{"name":"edi","id":"5aeeceaad0de5dcfb6dede5b"},"board":{"shortLink":"XPhODWYc","name":"Pembersihan Damija","id":"5afd62c82e7bcbe720ce0919"},"card":{"shortLink":"x5QIlTIG","idShort":6,"name":"Pemasangan Berjong","id":"5b27b75d46b9f6a6572c7252"},"idMember":"5aeeceaad0de5dcfb6dede5b"},"type":"addMemberToCard","date":"2018-06-18T13:45:33.378Z","limits":{},"member":{"id":"5aeeceaad0de5dcfb6dede5b","avatarHash":null,"avatarUrl":null,"fullName":"edi","initials":"E","username":"edi287"},"memberCreator":{"id":"5aeeceaad0de5dcfb6dede5b","avatarHash":null,"avatarUrl":null,"fullName":"edi","initials":"E","username":"edi287"}},{"id":"5b27b770b467b71561373e47","idMemberCreator":"5aeeceaad0de5dcfb6dede5b","data":{"list":{"name":"Pekerjaan","id":"5afd62d038a3f9714e1973ec"},"board":{"shortLink":"XPhODWYc","name":"Pembersihan Damija","id":"5afd62c82e7bcbe720ce0919"},"card":{"shortLink":"ECW85p9B","idShort":7,"name":"Berjong","id":"5b27b7678b7b6bb1de46e190","closed":true},"old":{"closed":false}},"type":"updateCard","date":"2018-06-18T13:45:20.587Z","limits":{},"memberCreator":{"id":"5aeeceaad0de5dcfb6dede5b","avatarHash":null,"avatarUrl":null,"fullName":"edi","initials":"E","username":"edi287"}},{"id":"5b27b7678b7b6bb1de46e191","idMemberCreator":"5aeeceaad0de5dcfb6dede5b","data":{"board":{"shortLink":"XPhODWYc","name":"Pembersihan Damija","id":"5afd62c82e7bcbe720ce0919"},"list":{"name":"Pekerjaan","id":"5afd62d038a3f9714e1973ec"},"card":{"shortLink":"ECW85p9B","idShort":7,"name":"Berjong","id":"5b27b7678b7b6bb1de46e190"}},"type":"createCard","date":"2018-06-18T13:45:11.642Z","limits":{},"memberCreator":{"id":"5aeeceaad0de5dcfb6dede5b","avatarHash":null,"avatarUrl":null,"fullName":"edi","initials":"E","username":"edi287"}},{"id":"5b27b75d46b9f6a6572c7253","idMemberCreator":"5aeeceaad0de5dcfb6dede5b","data":{"board":{"shortLink":"XPhODWYc","name":"Pembersihan Damija","id":"5afd62c82e7bcbe720ce0919"},"list":{"name":"Pekerjaan","id":"5afd62d038a3f9714e1973ec"},"card":{"shortLink":"x5QIlTIG","idShort":6,"name":"Pemasangan Berjong","id":"5b27b75d46b9f6a6572c7252"}},"type":"createCard","date":"2018-06-18T13:45:01.036Z","limits":{},"memberCreator":{"id":"5aeeceaad0de5dcfb6dede5b","avatarHash":null,"avatarUrl":null,"fullName":"edi","initials":"E","username":"edi287"}},{"id":"5b27b751155f255eb906111f","idMemberCreator":"5aeeceaad0de5dcfb6dede5b","data":{"board":{"shortLink":"XPhODWYc","name":"Pembersihan Damija","id":"5afd62c82e7bcbe720ce0919"},"list":{"name":"Pekerjaan","id":"5afd62d038a3f9714e1973ec"},"card":{"shortLink":"MZv5UFCK","idShort":5,"name":"Pemasangan Bata","id":"5b27b751155f255eb906111c"}},"type":"createCard","date":"2018-06-18T13:44:49.776Z","limits":{},"memberCreator":{"id":"5aeeceaad0de5dcfb6dede5b","avatarHash":null,"avatarUrl":null,"fullName":"edi","initials":"E","username":"edi287"}},{"id":"5b27b751155f255eb906111e","idMemberCreator":"5aeeceaad0de5dcfb6dede5b","data":{"member":{"name":"edi","id":"5aeeceaad0de5dcfb6dede5b"},"board":{"shortLink":"XPhODWYc","name":"Pembersihan Damija","id":"5afd62c82e7bcbe720ce0919"},"card":{"shortLink":"MZv5UFCK","idShort":5,"name":"Pemasangan Bata","id":"5b27b751155f255eb906111c"},"idMember":"5aeeceaad0de5dcfb6dede5b"},"type":"addMemberToCard","date":"2018-06-18T13:44:49.761Z","limits":{},"member":{"id":"5aeeceaad0de5dcfb6dede5b","avatarHash":null,"avatarUrl":null,"fullName":"edi","initials":"E","username":"edi287"},"memberCreator":{"id":"5aeeceaad0de5dcfb6dede5b","avatarHash":null,"avatarUrl":null,"fullName":"edi","initials":"E","username":"edi287"}},{"id":"5b27b745a92449ac2c2b81ce","idMemberCreator":"5aeeceaad0de5dcfb6dede5b","data":{"board":{"shortLink":"XPhODWYc","name":"Pembersihan Damija","id":"5afd62c82e7bcbe720ce0919"},"list":{"name":"Pekerjaan","id":"5afd62d038a3f9714e1973ec"},"card":{"shortLink":"0jxjJ2dH","idShort":4,"name":"Galian Selokan","id":"5b27b745a92449ac2c2b81cc"}},"type":"createCard","date":"2018-06-18T13:44:37.057Z","limits":{},"memberCreator":{"id":"5aeeceaad0de5dcfb6dede5b","avatarHash":null,"avatarUrl":null,"fullName":"edi","initials":"E","username":"edi287"}},{"id":"5b27b745a92449ac2c2b81cd","idMemberCreator":"5aeeceaad0de5dcfb6dede5b","data":{"member":{"name":"edi","id":"5aeeceaad0de5dcfb6dede5b"},"board":{"shortLink":"XPhODWYc","name":"Pembersihan Damija","id":"5afd62c82e7bcbe720ce0919"},"card":{"shortLink":"0jxjJ2dH","idShort":4,"name":"Galian Selokan","id":"5b27b745a92449ac2c2b81cc"},"idMember":"5aeeceaad0de5dcfb6dede5b"},"type":"addMemberToCard","date":"2018-06-18T13:44:37.044Z","limits":{},"member":{"id":"5aeeceaad0de5dcfb6dede5b","avatarHash":null,"avatarUrl":null,"fullName":"edi","initials":"E","username":"edi287"},"memberCreator":{"id":"5aeeceaad0de5dcfb6dede5b","avatarHash":null,"avatarUrl":null,"fullName":"edi","initials":"E","username":"edi287"}},{"id":"5b27b6f4b5794ed65c76f949","idMemberCreator":"5aeeceaad0de5dcfb6dede5b","data":{"listAfter":{"name":"Pekerjaan","id":"5afd62d038a3f9714e1973ec"},"listBefore":{"name":"Selesai","id":"5afd6465b03c84f27b5ae1e0"},"board":{"shortLink":"XPhODWYc","name":"Pembersihan Damija","id":"5afd62c82e7bcbe720ce0919"},"card":{"shortLink":"zKOFz6O1","idShort":1,"name":"Pemotongan rumput","id":"5afd62ffde88f325936678d5","idList":"5afd62d038a3f9714e1973ec"},"old":{"idList":"5afd6465b03c84f27b5ae1e0"}},"type":"updateCard","date":"2018-06-18T13:43:16.502Z","limits":{},"memberCreator":{"id":"5aeeceaad0de5dcfb6dede5b","avatarHash":null,"avatarUrl":null,"fullName":"edi","initials":"E","username":"edi287"}},{"id":"5b096c44f95bab0e5ca749fb","idMemberCreator":"5aeeceaad0de5dcfb6dede5b","data":{"list":{"name":"Sedang Dikerjakan","id":"5afd62d12d1baa563bcfa96c"},"board":{"shortLink":"XPhODWYc","name":"Pembersihan Damija","id":"5afd62c82e7bcbe720ce0919"},"card":{"shortLink":"TnMJggXB","idShort":2,"name":"Pembersihan rumput","id":"5afd63464a5545ec9f1089af","pos":16384},"old":{"pos":32768}},"type":"updateCard","date":"2018-05-26T14:16:36.740Z","limits":{},"memberCreator":{"id":"5aeeceaad0de5dcfb6dede5b","avatarHash":null,"avatarUrl":null,"fullName":"edi","initials":"E","username":"edi287"}},{"id":"5b096c44f95bab0e5ca749fa","idMemberCreator":"5aeeceaad0de5dcfb6dede5b","data":{"listAfter":{"name":"Sedang Dikerjakan","id":"5afd62d12d1baa563bcfa96c"},"listBefore":{"name":"Pekerjaan","id":"5afd62d038a3f9714e1973ec"},"board":{"shortLink":"XPhODWYc","name":"Pembersihan Damija","id":"5afd62c82e7bcbe720ce0919"},"card":{"shortLink":"TnMJggXB","idShort":2,"name":"Pembersihan rumput","id":"5afd63464a5545ec9f1089af","idList":"5afd62d12d1baa563bcfa96c"},"old":{"idList":"5afd62d038a3f9714e1973ec"}},"type":"updateCard","date":"2018-05-26T14:16:36.717Z","limits":{},"memberCreator":{"id":"5aeeceaad0de5dcfb6dede5b","avatarHash":null,"avatarUrl":null,"fullName":"edi","initials":"E","username":"edi287"}},{"id":"5b096c441ed3e25311ded374","idMemberCreator":"5aeeceaad0de5dcfb6dede5b","data":{"list":{"name":"Pekerjaan","id":"5afd62d038a3f9714e1973ec"},"board":{"shortLink":"XPhODWYc","name":"Pembersihan Damija","id":"5afd62c82e7bcbe720ce0919"},"card":{"shortLink":"sleu11ga","idShort":3,"name":"Hdhsj","id":"5b090cdd45d017f8675a2d6f","pos":40960},"old":{"pos":49152}},"type":"updateCard","date":"2018-05-26T14:16:36.074Z","limits":{},"memberCreator":{"id":"5aeeceaad0de5dcfb6dede5b","avatarHash":null,"avatarUrl":null,"fullName":"edi","initials":"E","username":"edi287"}},{"id":"5b096c441ed3e25311ded373","idMemberCreator":"5aeeceaad0de5dcfb6dede5b","data":{"list":{"name":"Pekerjaan","id":"5afd62d038a3f9714e1973ec"},"board":{"shortLink":"XPhODWYc","name":"Pembersihan Damija","id":"5afd62c82e7bcbe720ce0919"},"card":{"shortLink":"sleu11ga","idShort":3,"name":"Hdhsj","id":"5b090cdd45d017f8675a2d6f","closed":true},"old":{"closed":false}},"type":"updateCard","date":"2018-05-26T14:16:36.053Z","limits":{},"memberCreator":{"id":"5aeeceaad0de5dcfb6dede5b","avatarHash":null,"avatarUrl":null,"fullName":"edi","initials":"E","username":"edi287"}},{"id":"5b090cdd45d017f8675a2d70","idMemberCreator":"5aeeceaad0de5dcfb6dede5b","data":{"board":{"shortLink":"XPhODWYc","name":"Pembersihan Damija","id":"5afd62c82e7bcbe720ce0919"},"list":{"name":"Pekerjaan","id":"5afd62d038a3f9714e1973ec"},"card":{"shortLink":"sleu11ga","idShort":3,"name":"Hdhsj","id":"5b090cdd45d017f8675a2d6f"}},"type":"createCard","date":"2018-05-26T07:29:33.414Z","limits":{},"memberCreator":{"id":"5aeeceaad0de5dcfb6dede5b","avatarHash":null,"avatarUrl":null,"fullName":"edi","initials":"E","username":"edi287"}},{"id":"5afd660879cfdd1643364047","idMemberCreator":"5aeeceaad0de5dcfb6dede5b","data":{"board":{"shortLink":"XPhODWYc","name":"Pembersihan Damija","id":"5afd62c82e7bcbe720ce0919"},"checklist":{"name":"Checklist","id":"5afd660879cfdd1643364046"},"card":{"shortLink":"TnMJggXB","idShort":2,"name":"Pembersihan rumput","id":"5afd63464a5545ec9f1089af"}},"type":"addChecklistToCard","date":"2018-05-17T11:22:48.046Z","limits":{},"memberCreator":{"id":"5aeeceaad0de5dcfb6dede5b","avatarHash":null,"avatarUrl":null,"fullName":"edi","initials":"E","username":"edi287"}},{"id":"5afd646ab5054f42edacb441","idMemberCreator":"5aeeceaad0de5dcfb6dede5b","data":{"listAfter":{"name":"Selesai","id":"5afd6465b03c84f27b5ae1e0"},"listBefore":{"name":"Masalah","id":"5afd62d1729e8a07ec91e3db"},"board":{"shortLink":"XPhODWYc","name":"Pembersihan Damija","id":"5afd62c82e7bcbe720ce0919"},"card":{"shortLink":"zKOFz6O1","idShort":1,"name":"Pemotongan rumput","id":"5afd62ffde88f325936678d5","idList":"5afd6465b03c84f27b5ae1e0"},"old":{"idList":"5afd62d1729e8a07ec91e3db"}},"type":"updateCard","date":"2018-05-17T11:15:54.464Z","limits":{},"memberCreator":{"id":"5aeeceaad0de5dcfb6dede5b","avatarHash":null,"avatarUrl":null,"fullName":"edi","initials":"E","username":"edi287"}},{"id":"5afd6465b03c84f27b5ae1e1","idMemberCreator":"5aeeceaad0de5dcfb6dede5b","data":{"board":{"shortLink":"XPhODWYc","name":"Pembersihan Damija","id":"5afd62c82e7bcbe720ce0919"},"list":{"name":"Selesai","id":"5afd6465b03c84f27b5ae1e0"}},"type":"createList","date":"2018-05-17T11:15:49.118Z","limits":{},"memberCreator":{"id":"5aeeceaad0de5dcfb6dede5b","avatarHash":null,"avatarUrl":null,"fullName":"edi","initials":"E","username":"edi287"}},{"id":"5afd6455e64a58371bb275fc","idMemberCreator":"5aeeceaad0de5dcfb6dede5b","data":{"list":{"name":"Masalah","id":"5afd62d1729e8a07ec91e3db"},"board":{"shortLink":"XPhODWYc","name":"Pembersihan Damija","id":"5afd62c82e7bcbe720ce0919"},"card":{"shortLink":"zKOFz6O1","idShort":1,"name":"Pemotongan rumput","id":"5afd62ffde88f325936678d5"},"text":"Knpai @Edi"},"type":"commentCard","date":"2018-05-17T11:15:33.549Z","limits":{"reactions":{"perAction":{"status":"ok","disableAt":950,"warnAt":900},"uniquePerAction":{"status":"ok","disableAt":17,"warnAt":16}}},"memberCreator":{"id":"5aeeceaad0de5dcfb6dede5b","avatarHash":null,"avatarUrl":null,"fullName":"edi","initials":"E","username":"edi287"}},{"id":"5afd643d820d36555652ddce","idMemberCreator":"5aeeceaad0de5dcfb6dede5b","data":{"list":{"name":"Masalah","id":"5afd62d1729e8a07ec91e3db"},"board":{"shortLink":"XPhODWYc","name":"Pembersihan Damija","id":"5afd62c82e7bcbe720ce0919"},"card":{"shortLink":"zKOFz6O1","idShort":1,"name":"Pemotongan rumput","id":"5afd62ffde88f325936678d5"},"text":"kjdhddj"},"type":"commentCard","date":"2018-05-17T11:15:09.443Z","limits":{"reactions":{"perAction":{"status":"ok","disableAt":950,"warnAt":900},"uniquePerAction":{"status":"ok","disableAt":17,"warnAt":16}}},"memberCreator":{"id":"5aeeceaad0de5dcfb6dede5b","avatarHash":null,"avatarUrl":null,"fullName":"edi","initials":"E","username":"edi287"}},{"id":"5afd6434b1ba1aed79bc3e0c","idMemberCreator":"5aeeceaad0de5dcfb6dede5b","data":{"listAfter":{"name":"Masalah","id":"5afd62d1729e8a07ec91e3db"},"listBefore":{"name":"Sedang Dikerjakan","id":"5afd62d12d1baa563bcfa96c"},"board":{"shortLink":"XPhODWYc","name":"Pembersihan Damija","id":"5afd62c82e7bcbe720ce0919"},"card":{"shortLink":"zKOFz6O1","idShort":1,"name":"Pemotongan rumput","id":"5afd62ffde88f325936678d5","idList":"5afd62d1729e8a07ec91e3db"},"old":{"idList":"5afd62d12d1baa563bcfa96c"}},"type":"updateCard","date":"2018-05-17T11:15:00.543Z","limits":{},"memberCreator":{"id":"5aeeceaad0de5dcfb6dede5b","avatarHash":null,"avatarUrl":null,"fullName":"edi","initials":"E","username":"edi287"}},{"id":"5afd6429e8a1b0cee67a1af7","idMemberCreator":"5aeeceaad0de5dcfb6dede5b","data":{"board":{"shortLink":"XPhODWYc","name":"Pembersihan Damija","id":"5afd62c82e7bcbe720ce0919"},"list":{"id":"5afd62d1729e8a07ec91e3db","name":"Masalah"},"old":{"name":"Done"}},"type":"updateList","date":"2018-05-17T11:14:49.201Z","limits":{},"memberCreator":{"id":"5aeeceaad0de5dcfb6dede5b","avatarHash":null,"avatarUrl":null,"fullName":"edi","initials":"E","username":"edi287"}},{"id":"5afd640ba20b195dcaf965b6","idMemberCreator":"5aeeceaad0de5dcfb6dede5b","data":{"checkItem":{"state":"complete","name":"Daerah barru","id":"5afd6388ee3c317b61066217"},"checklist":{"name":"Checklist","id":"5afd637ecd18a8783d091a5d"},"card":{"shortLink":"zKOFz6O1","idShort":1,"name":"Pemotongan rumput","id":"5afd62ffde88f325936678d5"},"board":{"shortLink":"XPhODWYc","name":"Pembersihan Damija","id":"5afd62c82e7bcbe720ce0919"}},"type":"updateCheckItemStateOnCard","date":"2018-05-17T11:14:19.239Z","limits":{},"memberCreator":{"id":"5aeeceaad0de5dcfb6dede5b","avatarHash":null,"avatarUrl":null,"fullName":"edi","initials":"E","username":"edi287"}},{"id":"5afd6404682e61c472c45924","idMemberCreator":"5aeeceaad0de5dcfb6dede5b","data":{"board":{"shortLink":"XPhODWYc","name":"Pembersihan Damija","id":"5afd62c82e7bcbe720ce0919"},"list":{"id":"5afd62d12d1baa563bcfa96c","name":"Sedang Dikerjakan"},"old":{"name":"Doing"}},"type":"updateList","date":"2018-05-17T11:14:12.404Z","limits":{},"memberCreator":{"id":"5aeeceaad0de5dcfb6dede5b","avatarHash":null,"avatarUrl":null,"fullName":"edi","initials":"E","username":"edi287"}},{"id":"5afd63fd23fede05fa36f03a","idMemberCreator":"5aeeceaad0de5dcfb6dede5b","data":{"listAfter":{"name":"Doing","id":"5afd62d12d1baa563bcfa96c"},"listBefore":{"name":"Pekerjaan","id":"5afd62d038a3f9714e1973ec"},"board":{"shortLink":"XPhODWYc","name":"Pembersihan Damija","id":"5afd62c82e7bcbe720ce0919"},"card":{"shortLink":"zKOFz6O1","idShort":1,"name":"Pemotongan rumput","id":"5afd62ffde88f325936678d5","idList":"5afd62d12d1baa563bcfa96c"},"old":{"idList":"5afd62d038a3f9714e1973ec"}},"type":"updateCard","date":"2018-05-17T11:14:05.715Z","limits":{},"memberCreator":{"id":"5aeeceaad0de5dcfb6dede5b","avatarHash":null,"avatarUrl":null,"fullName":"edi","initials":"E","username":"edi287"}},{"id":"5afd63f012fa0464597ee659","idMemberCreator":"5aeeceaad0de5dcfb6dede5b","data":{"list":{"name":"Pekerjaan","id":"5afd62d038a3f9714e1973ec"},"board":{"shortLink":"XPhODWYc","name":"Pembersihan Damija","id":"5afd62c82e7bcbe720ce0919"},"card":{"shortLink":"zKOFz6O1","idShort":1,"name":"Pemotongan rumput","id":"5afd62ffde88f325936678d5","desc":"Pemotongan rumput"},"old":{"desc":""}},"type":"updateCard","date":"2018-05-17T11:13:52.889Z","limits":{},"memberCreator":{"id":"5aeeceaad0de5dcfb6dede5b","avatarHash":null,"avatarUrl":null,"fullName":"edi","initials":"E","username":"edi287"}},{"id":"5afd63bccaa37f9996e8a486","idMemberCreator":"5aeeceaad0de5dcfb6dede5b","data":{"list":{"name":"Pekerjaan","id":"5afd62d038a3f9714e1973ec"},"board":{"shortLink":"XPhODWYc","name":"Pembersihan Damija","id":"5afd62c82e7bcbe720ce0919"},"card":{"shortLink":"zKOFz6O1","idShort":1,"name":"Pemotongan rumput","id":"5afd62ffde88f325936678d5","idMembers":["5aeeceaad0de5dcfb6dede5b"]},"old":{"idMembers":["5aeeceaad0de5dcfb6dede5b"]}},"type":"updateCard","date":"2018-05-17T11:13:00.676Z","limits":{},"memberCreator":{"id":"5aeeceaad0de5dcfb6dede5b","avatarHash":null,"avatarUrl":null,"fullName":"edi","initials":"E","username":"edi287"}},{"id":"5afd63bccaa37f9996e8a485","idMemberCreator":"5aeeceaad0de5dcfb6dede5b","data":{"board":{"shortLink":"XPhODWYc","name":"Pembersihan Damija","id":"5afd62c82e7bcbe720ce0919"},"card":{"shortLink":"zKOFz6O1","idShort":1,"name":"Pemotongan rumput","id":"5afd62ffde88f325936678d5"},"idMember":"5aeeceaad0de5dcfb6dede5b"},"type":"addMemberToCard","date":"2018-05-17T11:13:00.664Z","limits":{},"member":{"id":"5aeeceaad0de5dcfb6dede5b","avatarHash":null,"avatarUrl":null,"fullName":"edi","initials":"E","username":"edi287"},"memberCreator":{"id":"5aeeceaad0de5dcfb6dede5b","avatarHash":null,"avatarUrl":null,"fullName":"edi","initials":"E","username":"edi287"}},{"id":"5afd63a918758c312c1c39bd","idMemberCreator":"5aeeceaad0de5dcfb6dede5b","data":{"list":{"name":"Pekerjaan","id":"5afd62d038a3f9714e1973ec"},"board":{"shortLink":"XPhODWYc","name":"Pembersihan Damija","id":"5afd62c82e7bcbe720ce0919"},"card":{"shortLink":"zKOFz6O1","idShort":1,"name":"Pemotongan rumput","id":"5afd62ffde88f325936678d5","dueComplete":false},"old":{"dueComplete":true}},"type":"updateCard","date":"2018-05-17T11:12:41.390Z","limits":{},"memberCreator":{"id":"5aeeceaad0de5dcfb6dede5b","avatarHash":null,"avatarUrl":null,"fullName":"edi","initials":"E","username":"edi287"}},{"id":"5afd63a8fe52b2ca211988b9","idMemberCreator":"5aeeceaad0de5dcfb6dede5b","data":{"list":{"name":"Pekerjaan","id":"5afd62d038a3f9714e1973ec"},"board":{"shortLink":"XPhODWYc","name":"Pembersihan Damija","id":"5afd62c82e7bcbe720ce0919"},"card":{"shortLink":"zKOFz6O1","idShort":1,"name":"Pemotongan rumput","id":"5afd62ffde88f325936678d5","dueComplete":true},"old":{"dueComplete":false}},"type":"updateCard","date":"2018-05-17T11:12:40.118Z","limits":{},"memberCreator":{"id":"5aeeceaad0de5dcfb6dede5b","avatarHash":null,"avatarUrl":null,"fullName":"edi","initials":"E","username":"edi287"}},{"id":"5afd63a6439cdbe4bb06599a","idMemberCreator":"5aeeceaad0de5dcfb6dede5b","data":{"list":{"name":"Pekerjaan","id":"5afd62d038a3f9714e1973ec"},"board":{"shortLink":"XPhODWYc","name":"Pembersihan Damija","id":"5afd62c82e7bcbe720ce0919"},"card":{"shortLink":"zKOFz6O1","idShort":1,"name":"Pemotongan rumput","id":"5afd62ffde88f325936678d5","due":"2018-05-20T01:00:00.000Z"},"old":{"due":null}},"type":"updateCard","date":"2018-05-17T11:12:38.905Z","limits":{},"memberCreator":{"id":"5aeeceaad0de5dcfb6dede5b","avatarHash":null,"avatarUrl":null,"fullName":"edi","initials":"E","username":"edi287"}},{"id":"5afd637ecd18a8783d091a5e","idMemberCreator":"5aeeceaad0de5dcfb6dede5b","data":{"board":{"shortLink":"XPhODWYc","name":"Pembersihan Damija","id":"5afd62c82e7bcbe720ce0919"},"checklist":{"name":"Checklist","id":"5afd637ecd18a8783d091a5d"},"card":{"shortLink":"zKOFz6O1","idShort":1,"name":"Pemotongan rumput","id":"5afd62ffde88f325936678d5"}},"type":"addChecklistToCard","date":"2018-05-17T11:11:58.181Z","limits":{},"memberCreator":{"id":"5aeeceaad0de5dcfb6dede5b","avatarHash":null,"avatarUrl":null,"fullName":"edi","initials":"E","username":"edi287"}},{"id":"5afd63464a5545ec9f1089b0","idMemberCreator":"5aeeceaad0de5dcfb6dede5b","data":{"board":{"shortLink":"XPhODWYc","name":"Pembersihan Damija","id":"5afd62c82e7bcbe720ce0919"},"list":{"name":"Pekerjaan","id":"5afd62d038a3f9714e1973ec"},"card":{"shortLink":"TnMJggXB","idShort":2,"name":"Pembersihan rumput","id":"5afd63464a5545ec9f1089af"}},"type":"createCard","date":"2018-05-17T11:11:02.265Z","limits":{},"memberCreator":{"id":"5aeeceaad0de5dcfb6dede5b","avatarHash":null,"avatarUrl":null,"fullName":"edi","initials":"E","username":"edi287"}},{"id":"5afd62ffde88f325936678d6","idMemberCreator":"5aeeceaad0de5dcfb6dede5b","data":{"board":{"shortLink":"XPhODWYc","name":"Pembersihan Damija","id":"5afd62c82e7bcbe720ce0919"},"list":{"name":"Pekerjaan","id":"5afd62d038a3f9714e1973ec"},"card":{"shortLink":"zKOFz6O1","idShort":1,"name":"Pemotongan rumput","id":"5afd62ffde88f325936678d5"}},"type":"createCard","date":"2018-05-17T11:09:51.919Z","limits":{},"memberCreator":{"id":"5aeeceaad0de5dcfb6dede5b","avatarHash":null,"avatarUrl":null,"fullName":"edi","initials":"E","username":"edi287"}},{"id":"5afd62e276f46ea8b53b4b4a","idMemberCreator":"5aeeceaad0de5dcfb6dede5b","data":{"board":{"shortLink":"XPhODWYc","name":"Pembersihan Damija","id":"5afd62c82e7bcbe720ce0919"},"list":{"id":"5afd62d038a3f9714e1973ec","name":"Pekerjaan"},"old":{"name":"To Do"}},"type":"updateList","date":"2018-05-17T11:09:22.491Z","limits":{},"memberCreator":{"id":"5aeeceaad0de5dcfb6dede5b","avatarHash":null,"avatarUrl":null,"fullName":"edi","initials":"E","username":"edi287"}},{"id":"5afd62d1729e8a07ec91e3dc","idMemberCreator":"5aeeceaad0de5dcfb6dede5b","data":{"board":{"shortLink":"XPhODWYc","name":"Pembersihan Damija","id":"5afd62c82e7bcbe720ce0919"},"list":{"name":"Done","id":"5afd62d1729e8a07ec91e3db"}},"type":"createList","date":"2018-05-17T11:09:05.943Z","limits":{},"memberCreator":{"id":"5aeeceaad0de5dcfb6dede5b","avatarHash":null,"avatarUrl":null,"fullName":"edi","initials":"E","username":"edi287"}},{"id":"5afd62d12d1baa563bcfa96d","idMemberCreator":"5aeeceaad0de5dcfb6dede5b","data":{"board":{"shortLink":"XPhODWYc","name":"Pembersihan Damija","id":"5afd62c82e7bcbe720ce0919"},"list":{"name":"Doing","id":"5afd62d12d1baa563bcfa96c"}},"type":"createList","date":"2018-05-17T11:09:05.386Z","limits":{},"memberCreator":{"id":"5aeeceaad0de5dcfb6dede5b","avatarHash":null,"avatarUrl":null,"fullName":"edi","initials":"E","username":"edi287"}},{"id":"5afd62d038a3f9714e1973ed","idMemberCreator":"5aeeceaad0de5dcfb6dede5b","data":{"board":{"shortLink":"XPhODWYc","name":"Pembersihan Damija","id":"5afd62c82e7bcbe720ce0919"},"list":{"name":"To Do","id":"5afd62d038a3f9714e1973ec"}},"type":"createList","date":"2018-05-17T11:09:04.877Z","limits":{},"memberCreator":{"id":"5aeeceaad0de5dcfb6dede5b","avatarHash":null,"avatarUrl":null,"fullName":"edi","initials":"E","username":"edi287"}},{"id":"5afd62c82e7bcbe720ce091b","idMemberCreator":"5aeeceaad0de5dcfb6dede5b","data":{"board":{"shortLink":"XPhODWYc","name":"Pembersihan Damija","id":"5afd62c82e7bcbe720ce0919"}},"type":"createBoard","date":"2018-05-17T11:08:56.871Z","limits":{},"memberCreator":{"id":"5aeeceaad0de5dcfb6dede5b","avatarHash":null,"avatarUrl":null,"fullName":"edi","initials":"E","username":"edi287"}}],"cards":[{"id":"5b090cdd45d017f8675a2d6f","checkItemStates":null,"closed":true,"dateLastActivity":"2018-05-26T14:16:36.072Z","desc":"","descData":null,"idBoard":"5afd62c82e7bcbe720ce0919","idList":"5afd62d038a3f9714e1973ec","idMembersVoted":[],"idShort":3,"idAttachmentCover":null,"limits":{"attachments":{"perCard":{"status":"ok","disableAt":950,"warnAt":900}},"checklists":{"perCard":{"status":"ok","disableAt":475,"warnAt":450}},"stickers":{"perCard":{"status":"ok","disableAt":67,"warnAt":63}}},"idLabels":[],"manualCoverAttachment":false,"name":"Hdhsj","pos":40960,"shortLink":"sleu11ga","badges":{"votes":0,"attachmentsByType":{"trello":{"board":0,"card":0}},"viewingMemberVoted":false,"subscribed":false,"fogbugz":"","checkItems":0,"checkItemsChecked":0,"comments":0,"attachments":0,"description":false,"due":null,"dueComplete":false},"dueComplete":false,"due":null,"email":"edi287+2q82dknf8m8xmlhe6or+2qc1vui93809glxggof+2e1tccpfsy@boards.trello.com","idChecklists":[],"idMembers":[],"labels":[],"shortUrl":"https://trello.com/c/sleu11ga","subscribed":false,"url":"https://trello.com/c/sleu11ga/3-hdhsj","attachments":[],"pluginData":[],"customFieldItems":[]},{"id":"5b27b751155f255eb906111c","checkItemStates":null,"closed":false,"dateLastActivity":"2018-06-18T13:44:49.758Z","desc":"","descData":null,"idBoard":"5afd62c82e7bcbe720ce0919","idList":"5afd62d038a3f9714e1973ec","idMembersVoted":[],"idShort":5,"idAttachmentCover":null,"limits":{"attachments":{"perCard":{"status":"ok","disableAt":950,"warnAt":900}},"checklists":{"perCard":{"status":"ok","disableAt":475,"warnAt":450}},"stickers":{"perCard":{"status":"ok","disableAt":67,"warnAt":63}}},"idLabels":[],"manualCoverAttachment":false,"name":"Pemasangan Bata","pos":147456,"shortLink":"MZv5UFCK","badges":{"votes":0,"attachmentsByType":{"trello":{"board":0,"card":0}},"viewingMemberVoted":false,"subscribed":true,"fogbugz":"","checkItems":0,"checkItemsChecked":0,"comments":0,"attachments":0,"description":false,"due":null,"dueComplete":false},"dueComplete":false,"due":null,"email":"edi287+2q82dknf8m8xmlhe6or+2qgpktlk148b4vb1t7g+1vcc72phej@boards.trello.com","idChecklists":[],"idMembers":["5aeeceaad0de5dcfb6dede5b"],"labels":[],"shortUrl":"https://trello.com/c/MZv5UFCK","subscribed":true,"url":"https://trello.com/c/MZv5UFCK/5-pemasangan-bata","attachments":[],"pluginData":[],"customFieldItems":[]},{"id":"5b27b75d46b9f6a6572c7252","checkItemStates":null,"closed":false,"dateLastActivity":"2018-06-18T13:45:33.375Z","desc":"","descData":null,"idBoard":"5afd62c82e7bcbe720ce0919","idList":"5afd62d038a3f9714e1973ec","idMembersVoted":[],"idShort":6,"idAttachmentCover":null,"limits":{"attachments":{"perCard":{"status":"ok","disableAt":950,"warnAt":900}},"checklists":{"perCard":{"status":"ok","disableAt":475,"warnAt":450}},"stickers":{"perCard":{"status":"ok","disableAt":67,"warnAt":63}}},"idLabels":[],"manualCoverAttachment":false,"name":"Pemasangan Berjong","pos":212992,"shortLink":"x5QIlTIG","badges":{"votes":0,"attachmentsByType":{"trello":{"board":0,"card":0}},"viewingMemberVoted":false,"subscribed":true,"fogbugz":"","checkItems":0,"checkItemsChecked":0,"comments":0,"attachments":0,"description":false,"due":null,"dueComplete":false},"dueComplete":false,"due":null,"email":"edi287+2q82dknf8m8xmlhe6or+2qgpkux0ui5wzj169g2+22ywdjhaft@boards.trello.com","idChecklists":[],"idMembers":["5aeeceaad0de5dcfb6dede5b"],"labels":[],"shortUrl":"https://trello.com/c/x5QIlTIG","subscribed":true,"url":"https://trello.com/c/x5QIlTIG/6-pemasangan-berjong","attachments":[],"pluginData":[],"customFieldItems":[]},{"id":"5b27b7678b7b6bb1de46e190","checkItemStates":null,"closed":true,"dateLastActivity":"2018-06-18T13:45:20.584Z","desc":"","descData":null,"idBoard":"5afd62c82e7bcbe720ce0919","idList":"5afd62d038a3f9714e1973ec","idMembersVoted":[],"idShort":7,"idAttachmentCover":null,"limits":{"attachments":{"perCard":{"status":"ok","disableAt":950,"warnAt":900}},"checklists":{"perCard":{"status":"ok","disableAt":475,"warnAt":450}},"stickers":{"perCard":{"status":"ok","disableAt":67,"warnAt":63}}},"idLabels":[],"manualCoverAttachment":false,"name":"Berjong","pos":278528,"shortLink":"ECW85p9B","badges":{"votes":0,"attachmentsByType":{"trello":{"board":0,"card":0}},"viewingMemberVoted":false,"subscribed":false,"fogbugz":"","checkItems":0,"checkItemsChecked":0,"comments":0,"attachments":0,"description":false,"due":null,"dueComplete":false},"dueComplete":false,"due":null,"email":"edi287+2q82dknf8m8xmlhe6or+2qgpkw0zzh5pr6lyys0+103qiene98@boards.trello.com","idChecklists":[],"idMembers":[],"labels":[],"shortUrl":"https://trello.com/c/ECW85p9B","subscribed":false,"url":"https://trello.com/c/ECW85p9B/7-berjong","attachments":[],"pluginData":[],"customFieldItems":[]},{"id":"5afd63464a5545ec9f1089af","checkItemStates":null,"closed":false,"dateLastActivity":"2018-05-26T14:16:36.737Z","desc":"","descData":null,"idBoard":"5afd62c82e7bcbe720ce0919","idList":"5afd62d12d1baa563bcfa96c","idMembersVoted":[],"idShort":2,"idAttachmentCover":null,"limits":{"attachments":{"perCard":{"status":"ok","disableAt":950,"warnAt":900}},"checklists":{"perCard":{"status":"ok","disableAt":475,"warnAt":450}},"stickers":{"perCard":{"status":"ok","disableAt":67,"warnAt":63}}},"idLabels":[],"manualCoverAttachment":false,"name":"Pembersihan rumput","pos":16384,"shortLink":"TnMJggXB","badges":{"votes":0,"attachmentsByType":{"trello":{"board":0,"card":0}},"viewingMemberVoted":false,"subscribed":false,"fogbugz":"","checkItems":1,"checkItemsChecked":0,"comments":0,"attachments":0,"description":false,"due":null,"dueComplete":false},"dueComplete":false,"due":null,"email":"edi287+2q82dknf8m8xmlhe6or+2qaa3xr7y4zi6obd5tb+0wtmcdsrmr@boards.trello.com","idChecklists":["5afd660879cfdd1643364046"],"idMembers":[],"labels":[],"shortUrl":"https://trello.com/c/TnMJggXB","subscribed":false,"url":"https://trello.com/c/TnMJggXB/2-pembersihan-rumput","attachments":[],"pluginData":[],"customFieldItems":[]},{"id":"5b27b745a92449ac2c2b81cc","checkItemStates":null,"closed":false,"dateLastActivity":"2018-06-18T13:45:46.037Z","desc":"","descData":null,"idBoard":"5afd62c82e7bcbe720ce0919","idList":"5afd62d1729e8a07ec91e3db","idMembersVoted":[],"idShort":4,"idAttachmentCover":null,"limits":{"attachments":{"perCard":{"status":"ok","disableAt":950,"warnAt":900}},"checklists":{"perCard":{"status":"ok","disableAt":475,"warnAt":450}},"stickers":{"perCard":{"status":"ok","disableAt":67,"warnAt":63}}},"idLabels":[],"manualCoverAttachment":false,"name":"Galian Selokan","pos":81920,"shortLink":"0jxjJ2dH","badges":{"votes":0,"attachmentsByType":{"trello":{"board":0,"card":0}},"viewingMemberVoted":false,"subscribed":true,"fogbugz":"","checkItems":0,"checkItemsChecked":0,"comments":0,"attachments":0,"description":false,"due":null,"dueComplete":false},"dueComplete":false,"due":null,"email":"edi287+2q82dknf8m8xmlhe6or+2qgpksd34rxmjjccs7g+1sai5gxw6t@boards.trello.com","idChecklists":[],"idMembers":["5aeeceaad0de5dcfb6dede5b"],"labels":[],"shortUrl":"https://trello.com/c/0jxjJ2dH","subscribed":true,"url":"https://trello.com/c/0jxjJ2dH/4-galian-selokan","attachments":[],"pluginData":[],"customFieldItems":[]},{"id":"5afd62ffde88f325936678d5","checkItemStates":null,"closed":false,"dateLastActivity":"2018-06-18T13:45:43.078Z","desc":"Pemotongan rumput","descData":{"emoji":{}},"idBoard":"5afd62c82e7bcbe720ce0919","idList":"5afd6465b03c84f27b5ae1e0","idMembersVoted":[],"idShort":1,"idAttachmentCover":null,"limits":{"attachments":{"perCard":{"status":"ok","disableAt":950,"warnAt":900}},"checklists":{"perCard":{"status":"ok","disableAt":475,"warnAt":450}},"stickers":{"perCard":{"status":"ok","disableAt":67,"warnAt":63}}},"idLabels":[],"manualCoverAttachment":false,"name":"Pemotongan rumput","pos":16384,"shortLink":"zKOFz6O1","badges":{"votes":0,"attachmentsByType":{"trello":{"board":0,"card":0}},"viewingMemberVoted":false,"subscribed":true,"fogbugz":"","checkItems":2,"checkItemsChecked":1,"comments":2,"attachments":0,"description":true,"due":"2018-05-20T01:00:00.000Z","dueComplete":false},"dueComplete":false,"due":"2018-05-20T01:00:00.000Z","email":"edi287+2q82dknf8m8xmlhe6or+2qaa3q52gbcncumkyc5+09xfzhmfr8@boards.trello.com","idChecklists":["5afd637ecd18a8783d091a5d"],"idMembers":["5aeeceaad0de5dcfb6dede5b"],"labels":[],"shortUrl":"https://trello.com/c/zKOFz6O1","subscribed":true,"url":"https://trello.com/c/zKOFz6O1/1-pemotongan-rumput","attachments":[],"pluginData":[],"customFieldItems":[]}],"labels":[{"id":"5afd62cc00849d3b29dda202","idBoard":"5afd62c82e7bcbe720ce0919","name":"","color":"green"},{"id":"5afd62cdbd876d1eadeb2367","idBoard":"5afd62c82e7bcbe720ce0919","name":"","color":"yellow"},{"id":"5afd62cec893fd01b98386cf","idBoard":"5afd62c82e7bcbe720ce0919","name":"","color":"orange"},{"id":"5afd62cef5f10977c0a3e9d4","idBoard":"5afd62c82e7bcbe720ce0919","name":"","color":"red"},{"id":"5afd62cf569e15d76729048c","idBoard":"5afd62c82e7bcbe720ce0919","name":"","color":"purple"},{"id":"5afd62cf1a95e4f84ffe5da5","idBoard":"5afd62c82e7bcbe720ce0919","name":"","color":"blue"}],"lists":[{"id":"5afd62d038a3f9714e1973ec","name":"Pekerjaan","closed":false,"idBoard":"5afd62c82e7bcbe720ce0919","pos":16384,"subscribed":false,"limits":{"cards":{"openPerList":{"status":"ok","disableAt":4750,"warnAt":4500},"totalPerList":{"status":"ok","disableAt":950000,"warnAt":900000}}}},{"id":"5afd62d12d1baa563bcfa96c","name":"Sedang Dikerjakan","closed":false,"idBoard":"5afd62c82e7bcbe720ce0919","pos":32768,"subscribed":false,"limits":{"cards":{"openPerList":{"status":"ok","disableAt":4750,"warnAt":4500},"totalPerList":{"status":"ok","disableAt":950000,"warnAt":900000}}}},{"id":"5afd62d1729e8a07ec91e3db","name":"Masalah","closed":false,"idBoard":"5afd62c82e7bcbe720ce0919","pos":49152,"subscribed":false,"limits":{"cards":{"openPerList":{"status":"ok","disableAt":4750,"warnAt":4500},"totalPerList":{"status":"ok","disableAt":950000,"warnAt":900000}}}},{"id":"5afd6465b03c84f27b5ae1e0","name":"Selesai","closed":false,"idBoard":"5afd62c82e7bcbe720ce0919","pos":65536,"subscribed":false,"limits":{"cards":{"openPerList":{"status":"ok","disableAt":4750,"warnAt":4500},"totalPerList":{"status":"ok","disableAt":950000,"warnAt":900000}}}}],"members":[{"id":"5aeeceaad0de5dcfb6dede5b","avatarHash":null,"avatarUrl":null,"bio":"","bioData":null,"confirmed":true,"fullName":"edi","idEnterprisesDeactivated":[],"idPremOrgsAdmin":[],"initials":"E","memberType":"normal","products":[],"status":"disconnected","url":"https://trello.com/edi287","username":"edi287"}],"checklists":[{"id":"5afd637ecd18a8783d091a5d","name":"Checklist","idBoard":"5afd62c82e7bcbe720ce0919","idCard":"5afd62ffde88f325936678d5","pos":16384,"limits":{"checkItems":{"perChecklist":{"status":"ok","disableAt":190,"warnAt":180}}},"checkItems":[{"state":"complete","idChecklist":"5afd637ecd18a8783d091a5d","id":"5afd6388ee3c317b61066217","name":"Daerah barru","nameData":null,"pos":16384},{"state":"incomplete","idChecklist":"5afd637ecd18a8783d091a5d","id":"5afd638f97dcb8351a852545","name":"Daerah pekkae","nameData":null,"pos":32768}]},{"id":"5afd660879cfdd1643364046","name":"Checklist","idBoard":"5afd62c82e7bcbe720ce0919","idCard":"5afd63464a5545ec9f1089af","pos":16384,"limits":{"checkItems":{"perChecklist":{"status":"ok","disableAt":190,"warnAt":180}}},"checkItems":[{"state":"incomplete","idChecklist":"5afd660879cfdd1643364046","id":"5b096c4289b22e93a2fe12fa","name":"Target Volume 1 minggu","nameData":null,"pos":16384}]}],"customFields":[],"memberships":[{"id":"5afd62c82e7bcbe720ce091a","idMember":"5aeeceaad0de5dcfb6dede5b","memberType":"admin","unconfirmed":false,"deactivated":false}],"pluginData":[]}